{
  "groups": [
    {
      "name": "Kafka properties",
      "type": "ru.quipy.kafka.core.KafkaProperties",
      "sourceType": "ru.quipy.kafka.core.KafkaProperties"
    }
  ],
  "properties": [
    {
      "name": "kafka.bootstrap-servers",
      "type": "java.lang.String",
      "sourceType": "ru.quipy.kafka.core.KafkaProperties",
      "defaultValue": null
    },
    {
      "name": "kafka.scan-public-api-package",
      "type": "java.lang.String",
      "sourceType": "ru.quipy.kafka.core.KafkaProperties",
      "defaultValue": null
    },
    {
      "name": "kafka.replication-factor",
      "type": "java.lang.Short",
      "sourceType": "ru.quipy.kafka.core.KafkaProperties",
      "defaultValue": 1
    },
    {
      "name": "kafka.partitions",
      "type": "java.lang.Integer",
      "sourceType": "ru.quipy.kafka.core.KafkaProperties",
      "defaultValue": 5
    },
    {
      "name": "kafka.acks",
      "type": "java.lang.String",
      "sourceType": "ru.quipy.kafka.core.KafkaProperties",
      "defaultValue": "all"
    },
    {
      "name": "kafka.retries",
      "type": "java.lang.Integer",
      "sourceType": "ru.quipy.kafka.core.KafkaProperties",
      "defaultValue": 3
    },
    {
      "name": "kafka.batch-size",
      "type": "java.lang.Integer",
      "sourceType": "ru.quipy.kafka.core.KafkaProperties",
      "defaultValue": 16384
    },
    {
      "name": "kafka.linger-ms",
      "type": "java.lang.Integer",
      "sourceType": "ru.quipy.kafka.core.KafkaProperties",
      "defaultValue": 1
    },
    {
      "name": "kafka.buffer-memory",
      "type": "java.lang.Integer",
      "sourceType": "ru.quipy.kafka.core.KafkaProperties",
      "defaultValue": 33554432
    }
  ]
}
